source_mailjet_mail/__init__.py
source_mailjet_mail/manifest.yaml
source_mailjet_mail/run.py
source_mailjet_mail/source.py
airbyte_source_mailjet_mail-0.1.16.dist-info/METADATA
airbyte_source_mailjet_mail-0.1.16.dist-info/WHEEL
airbyte_source_mailjet_mail-0.1.16.dist-info/entry_points.txt
airbyte_source_mailjet_mail-0.1.16.dist-info/RECORD
